pulumi_gcp_pufferpanel/__init__.py
pulumi_gcp_pufferpanel/cloud_function/main.py
pulumi_gcp_pufferpanel/cloud_function/requirements.txt
pulumi_gcp_pufferpanel/cloud_function/startup.sh
pulumi_gcp_pufferpanel/pulumi_gcp_pufferpanel.py
pulumi_gcp_pufferpanel-0.3.0.dist-info/LICENSE.rst
pulumi_gcp_pufferpanel-0.3.0.dist-info/WHEEL
pulumi_gcp_pufferpanel-0.3.0.dist-info/METADATA
pulumi_gcp_pufferpanel-0.3.0.dist-info/RECORD
