Metadata-Version: 2.1
Name: pulumi-gcp-pufferpanel
Version: 0.3.0
Summary: Pulumi ComponentResource for running PufferPanel on GCP
Home-page: https://github.com/briankanya/pulumi-gcp-pufferpanel
Keywords: csgo,minecraft,pufferpanel
Author: Brian Kanya
Author-email: briankanya@gmail.com
Requires-Python: >=3.7,<4
Classifier: Development Status :: 2 - Pre-Alpha
Classifier: Intended Audience :: Developers
Classifier: License :: OSI Approved :: GNU General Public License v3 (GPLv3)
Classifier: Natural Language :: English
Classifier: Programming Language :: Python :: 3
Classifier: Programming Language :: Python :: 3.10
Classifier: Programming Language :: Python :: 3.7
Classifier: Programming Language :: Python :: 3.8
Classifier: Programming Language :: Python :: 3.9
Requires-Dist: pulumi-gcp (>=6.23.0,<7.0.0)
Project-URL: Bug Tracker, https://github.com/briankanya/pulumi-gcp-pufferpanel/issues
Project-URL: Documentation, https://pulumi-gcp-pufferpanel.readthedocs.io
Project-URL: Repository, https://github.com/briankanya/pulumi-gcp-pufferpanel
